CHANGES.rst
CONTRIBUTORS.rst
MANIFEST.in
README.rst
VERSION
setup.cfg
setup.py
test.rst
docs/LICENSE.GPL
docs/LICENSE.rst
docs/index.rst
src/visaplan/__init__.py
src/visaplan.plone.browsers.egg-info/PKG-INFO
src/visaplan.plone.browsers.egg-info/SOURCES.txt
src/visaplan.plone.browsers.egg-info/dependency_links.txt
src/visaplan.plone.browsers.egg-info/entry_points.txt
src/visaplan.plone.browsers.egg-info/namespace_packages.txt
src/visaplan.plone.browsers.egg-info/not-zip-safe
src/visaplan.plone.browsers.egg-info/requires.txt
src/visaplan.plone.browsers.egg-info/top_level.txt
src/visaplan/plone/__init__.py
src/visaplan/plone/browsers/__init__.py
src/visaplan/plone/browsers/configure.zcml
src/visaplan/plone/browsers/additionallanguages/__init__.py
src/visaplan/plone/browsers/additionallanguages/browser.py
src/visaplan/plone/browsers/additionallanguages/configure.zcml
src/visaplan/plone/browsers/advertisement/__init__.py
src/visaplan/plone/browsers/advertisement/browser.py
src/visaplan/plone/browsers/advertisement/configure.zcml
src/visaplan/plone/browsers/advertisement/util.py
src/visaplan/plone/browsers/advertisement/resource/unitracc-ads.js
src/visaplan/plone/browsers/advertisement/templates/__init__.py
src/visaplan/plone/browsers/advertisement/templates/ad_content.pt
src/visaplan/plone/browsers/advertisement/templates/ads_above_content.pt
src/visaplan/plone/browsers/advertisement/templates/ads_skyscraper.pt
src/visaplan/plone/browsers/advertisement/templates/ads_top_right.pt
src/visaplan/plone/browsers/advertisement/templates/configure.zcml
src/visaplan/plone/browsers/article/__init__.py
src/visaplan/plone/browsers/article/browser.py
src/visaplan/plone/browsers/article/configure.zcml
src/visaplan/plone/browsers/article/utils.py
src/visaplan/plone/browsers/article/templates/__init__.py
src/visaplan/plone/browsers/article/templates/configure.zcml
src/visaplan/plone/browsers/article/templates/unitraccarticle_macros.pt
src/visaplan/plone/browsers/author/__init__.py
src/visaplan/plone/browsers/author/browser.py
src/visaplan/plone/browsers/author/configure.zcml
src/visaplan/plone/browsers/author/utils.py
src/visaplan/plone/browsers/booking/__init__.py
src/visaplan/plone/browsers/booking/crumbs.py
src/visaplan/plone/browsers/changestate/__init__.py
src/visaplan/plone/browsers/changestate/browser.py
src/visaplan/plone/browsers/changestate/configure.zcml
